sobel_data_modulate/sobel_data_modulate.v
`timescale 1ps/1ps

module sobel_data_modulate (
    input clk,
    input rst,

    input [7:0] d0_i, // input pixel
    input [7:0] d1_i, // fifo line buffer 1 output pixel
    input [7:0] d2_i, // fifo line buffer 2 output pixel
    input done_i,

    output reg [7:0] d0_o,
    output reg [7:0] d1_o,
    output reg [7:0] d2_o,
    output reg [7:0] d3_o,
    output reg [7:0] d4_o,
    output reg [7:0] d5_o,
    output reg [7:0] d6_o,
    output reg [7:0] d7_o,
    output reg [7:0] d8_o,

    output done_o
);

// localparam ROWS = 5; // for unit testing
// localparam COLS = 6; // for unit testing
localparam ROWS = 128;
localparam COLS = 128;

reg [9:0] iRows, iCols;

reg [7:0] data0, data1, data2, data3, data4, data5, data6, data7, data8;
reg [7:0] iCounter;


assign done_o = (iCounter == 2) ? 1'b1 : 1'b0;

//-------------------------handle with iRows and iCols ---------------------
always @(posedge clk) begin
    if(rst) begin
        iRows <= 10'b0;
        iCols <= 10'b0;
    end else begin
        if(done_o == 1'b1) begin
            iCols <= (iCols == COLS - 1) ? 0 : iCols + 1;
            if(iCols == COLS - 1) 
                iRows <= (iRows == ROWS - 1) ? 0 : iRows + 1;
        end
    end
end

//-------------------------handle with 9 output data ---------------------
//-----d0 d1 d2 -----
//-----d3 d4 d5 -----
//-----d6 d7 d8 -----

always @(*) begin
    if(rst) begin
        d0_o = 0;
        d1_o = 0;
        d2_o = 0;
        d3_o = 0;
        d4_o = 0;
        d5_o = 0;
        d6_o = 0;
        d7_o = 0;
        d8_o = 0;
    end else begin
        if(done_o == 1'b1) begin
            //----pos 1---- the top left edge point
            if(iRows == 0 && iCols == 0) begin
                d0_o = 0;
                d1_o = 0;
                d2_o = 0;
                d3_o = 0;
                d4_o = data4;
                d5_o = data5;
                d6_o = 0;
                d7_o = data7;
                d8_o = data8;
            //----pos 2---- the fist row points
            end else if(iRows == 0 && iCols > 0 && iCols < COLS - 1) begin
                d0_o = 0;
                d1_o = 0;
                d2_o = 0;
                d3_o = data3;
                d4_o = data4;
                d5_o = data5;
                d6_o = data6;
                d7_o = data7;
                d8_o = data8;
            //----pos 3---- the top right edge point
            end else if(iRows == 0 && iCols == COLS - 1) begin
                d0_o = 0;
                d1_o = 0;
                d2_o = 0;
                d3_o = data3;
                d4_o = data4;
                d5_o = 0;
                d6_o = data6;
                d7_o = data7;
                d8_o = 0;
            //----pos 4---- the left edge points
            end else if(iRows > 0 && iRows < ROWS - 1 && iCols == 0) begin
                d0_o = 0;
                d1_o = data1;
                d2_o = data2;
                d3_o = 0;
                d4_o = data4;
                d5_o = data5;
                d6_o = 0;
                d7_o = data7;
                d8_o = data8;
            //----pos 5---- the fully internal points
            end else if(iRows > 0 && iRows < ROWS - 1 && iCols > 0 && iCols < COLS - 1) begin
                d0_o = data0;
                d1_o = data1;
                d2_o = data2;
                d3_o = data3;
                d4_o = data4;
                d5_o = data5;
                d6_o = data6;
                d7_o = data7;
                d8_o = data8;
            //----pos 6---- the right edge points
            end else if(iRows > 0 && iRows < ROWS - 1 && iCols == COLS - 1) begin
                d0_o = data0;
                d1_o = data1;
                d2_o = 0;
                d3_o = data3;
                d4_o = data4;
                d5_o = 0;
                d6_o = data6;
                d7_o = data7;
                d8_o = 0;
            //----pos 7---- the bottom left edge point
            end else if(iRows == ROWS - 1 && iCols == 0) begin
                d0_o = 0;
                d1_o = data1;
                d2_o = data2;
                d3_o = 0;
                d4_o = data4;
                d5_o = data5;
                d6_o = 0;
                d7_o = 0;
                d8_o = 0;
            //----pos 8---- the bottom edge points
            end else if(iRows == ROWS - 1 && iCols > 0 && iCols < COLS - 1) begin
                d0_o = data0;
                d1_o = data1;
                d2_o = data2;
                d3_o = data3;
                d4_o = data4;
                d5_o = data5;
                d6_o = 0;
                d7_o = 0;
                d8_o = 0;
            //----pos 9---- the bottom right edge point
            end else if(iRows == ROWS - 1 && iCols == COLS - 1) begin
                d0_o = data0;
                d1_o = data1;
                d2_o = 0;
                d3_o = data3;
                d4_o = data4;
                d5_o = 0;
                d6_o = 0;
                d7_o = 0;
                d8_o = 0;
            end
        end
    end
end

//-------------------------handle with iCounter------------------
// the iCounter is used to track the number of columns received
// so far. We can only modulate data when all 9 pixels (i.e. 3 columns)
// are available.
always @(posedge clk) begin
    if(rst) begin
        iCounter <= 8'b0;
    end else begin
        if(done_i == 1'b1) begin
            iCounter <= (iCounter == 2) ? iCounter : iCounter + 8'b1;
        end
    end
end

//-------------------------shift data-------------------------
always @(posedge clk) begin
    if(rst) begin
        data0 <= 8'b0;
        data1 <= 8'b0;
        data2 <= 8'b0;
        data3 <= 8'b0;
        data4 <= 8'b0;
        data5 <= 8'b0;
        data6 <= 8'b0;
        data7 <= 8'b0;
        data8 <= 8'b0;
    end else begin
        if(done_i == 1'b1) begin
            // these 3 lines correspond to the rightmost 3 bits,
            // where d2 comes from the output of fifo line buffer 2
            data0 <= data1;
            data1 <= data2;
            data2 <= d2_i;

            // these 3 lines correspond to the middle 3 bits,
            // where d5 comes from the output of fifo line buffer 1
            data3 <= data4;
            data4 <= data5;
            data5 <= d1_i;

            // these 3 lines correspond to the leftmost 3 bits,
            // where d5 comes from pixel input
            data6 <= data7;
            data7 <= data8;
            data8 <= d0_i;
        end
    end

end

endmodule

fifo_single_line_buffer/fifo_single_line_buffer.v
`timescale 1ps/1ps

// The implementation for a single buffer such as fifo Line buffer 1
// if there is continuous data stream filling the fifo, then once the fifo
// is full the fifo data will be read continuously, while the input data
// continue writing to the fifo. --> This is effectively shifting data out
// from the fifo while new data is shifting into the fifo.
module fifo_single_line_buffer (
    input clk,
    input rst,
    input we_i,

    input [7:0] data_i,
    output [7:0] data_o,
    output done_o
);
    // This suggests that the buffer is designed to hold 640 pixel values 
    // (often corresponding to the width of an image in a row). 
    // parameter DEPTH = 640;
    parameter DEPTH = 6; // for sim
    reg [7:0] mem [DEPTH - 1: 0];

    reg [9:0] wr_pointer; // we need 10 bits because we need 10 bits to cover 640
    reg [9:0] rd_pointer;
    //  A 10-bit counter used to track how many pixels have been written into the FIFO buffer. 
    // When it reaches DEPTH, it indicates that the FIFO is full.
    reg [9:0] iCounter;
    // This output signal indicates whether the FIFO has been filled with data or not. 
    assign done_o = (iCounter == DEPTH) ? 1'b1 : 1'b0;
    assign data_o = mem[rd_pointer];

    //------------------- Handle with iCounter --------------------
    // we can see that the iCounter is used to determine when the FIFO is full.
    always @(posedge clk) begin
        if(rst) begin
            iCounter <= 10'b0;
        end else begin
            if(we_i == 1'b1) begin
                iCounter <= (iCounter == DEPTH ) ? iCounter : iCounter + 10'b1;
            end
        end
    end

    //------------------- Handle with write process --------------------
    always @(posedge clk) begin
        if(rst) begin
            wr_pointer <= 10'b0;
        end else begin
            if(we_i == 1'b1) begin
                mem[wr_pointer] <= data_i;
                wr_pointer <= (wr_pointer == DEPTH - 1) ? 0 : wr_pointer + 10'b1;
            end
        end
    end

    //------------------- Handle with read process --------------------
    always @(posedge clk) begin
        if(rst) begin
            rd_pointer <= 10'b0;
        end else begin
            // The read pointer is updated after each read once the buffer has been filled.
            if(iCounter == DEPTH) begin
                rd_pointer <= (rd_pointer == DEPTH - 1) ? 0 : rd_pointer + 10'b1;
            end
        end
    end

endmodule

fifo_double_line_buffer/fifo_double_line_buffer.v
`timescale 1ps/1ps
`include "../fifo_single_line_buffer/fifo_single_line_buffer.v"

module fifo_double_line_buffer (
    input clk,
    input rst,
    input we_i,

    input [7:0] data_i,
    output [7:0] data0_o,
    output [7:0] data1_o,
    output [7:0] data2_o,
    output done_o
);

wire [7:0] fifo1_data, fifo2_data;
wire fifo1_done, fifo2_done;

assign data0_o = data_i;
assign data1_o = fifo1_data;
assign data2_o = fifo2_data;
assign done_o = fifo1_done;

fifo_single_line_buffer FIFO_SINGLE_LINE_BUFFER_01 (
    .clk(clk),
    .rst(rst),
    .we_i(we_i),

    .data_i(data_i),
    .data_o(fifo1_data),
    .done_o(fifo1_done)
);

fifo_single_line_buffer FIFO_SINGLE_LINE_BUFFER_02 (
    .clk(clk),
    .rst(rst),
    .we_i(fifo1_done),

    .data_i(fifo1_data),
    .data_o(fifo2_data),
    .done_o(fifo2_done)
);

endmodule

sobel_data_buffer/sobel_data_buffer.v
`timescale 1ps/1ps
`include "../fifo_double_line_buffer/fifo_double_line_buffer.v"
`include "../sobel_data_modulate/sobel_data_modulate.v"

module sobel_data_buffer (
    input clk,
    input rst,

    input [7:0] grayscale_i,
    input done_i,

    output [7:0] d0_o,
    output [7:0] d1_o,
    output [7:0] d2_o,
    output [7:0] d3_o,
    output [7:0] d4_o,
    output [7:0] d5_o,
    output [7:0] d6_o,
    output [7:0] d7_o,
    output [7:0] d8_o,
    output done_o
);

wire [7:0] double_line_buffer_data0;
wire [7:0] double_line_buffer_data1;
wire [7:0] double_line_buffer_data2;
wire double_line_buffer_done;

//------------------ fifo double line buffer ----------------
fifo_double_line_buffer FIFO_DOUBLE_LINE_BUFFER (

    .clk(clk),
    .rst(rst),

    .we_i(done_i),
    .data_i(grayscale_i),

    .data0_o(double_line_buffer_data0),
    .data1_o(double_line_buffer_data1),
    .data2_o(double_line_buffer_data2),

    .done_o(double_line_buffer_done)
);

sobel_data_modulate SOBEL_DATA_MODULATE(

    .clk(clk),
    .rst(rst),

    .d0_i(double_line_buffer_data0), 
    .d1_i(double_line_buffer_data1),
    .d2_i(double_line_buffer_data2),
    .done_i(double_line_buffer_done),

    .d0_o(d0_o),
    .d1_o(d1_o),
    .d2_o(d2_o),
    .d3_o(d3_o),
    .d4_o(d4_o),
    .d5_o(d5_o),
    .d6_o(d6_o),
    .d7_o(d7_o),
    .d8_o(d8_o),

    .done_o(done_o)
);





endmodule

sobel_data_buffer/sobel_data_buffer_tb.sv
`timescale 1ps/1ps
`include "sobel_data_buffer.v"
`define clk_period  10


module sobel_data_buffer_tb();

reg clk, rst;
reg [7:0] grayscale_i;
reg done_i;
wire [7:0] d0_o, d1_o, d2_o,
            d3_o, d4_o, d5_o,
            d6_o, d7_o, d8_o;


sobel_data_buffer SOBEL_DATA_BUFFER (

    .clk(clk),
    .rst(rst),

    .grayscale_i(grayscale_i), 
    .done_i(done_i),

    .d0_o(d0_o),
    .d1_o(d1_o),
    .d2_o(d2_o),
    .d3_o(d3_o),
    .d4_o(d4_o),
    .d5_o(d5_o),
    .d6_o(d6_o),
    .d7_o(d7_o),
    .d8_o(d8_o),

    .done_o(done_o)
);

initial clk = 1'b1;
always#(`clk_period / 2) clk = ~clk;

integer i;

initial begin
   rst = 1'b1;
   grayscale_i = 8'b0;
   done_i = 1'b0;

   $dumpfile("waveforms/sobel_data_buffer.vcd");
   $dumpvars(0, sobel_data_buffer_tb);

   #(`clk_period);
    rst = 1'b0;
    done_i = 1'b1;

    //------------------------
    //---01 02 03 04 05 06 ---
    //---07 08 09 10 11 12 ---
    //---13 14 15 16 17 18 ---
    //---19 20 21 22 23 24 ---
    //---25 26 27 28 29 30 ---
    //------------------------

    // we store one more line of data
    for(i = 1; i <= 36; i = i + 1) begin
        grayscale_i = i;
        #(`clk_period);
    end

    done_i = 1'b0;

    #(`clk_period);
    $stop;
end

endmodule

sobel_data_buffer/waveforms/sobel_data_buffer.vcd
$date
	Sun Mar 16 10:44:51 2025
$end
$version
	Icarus Verilog
$end
$timescale
	1ps
$end
$scope module sobel_data_buffer_tb $end
$var wire 1 ! done_o $end
$var wire 8 " d8_o [7:0] $end
$var wire 8 # d7_o [7:0] $end
$var wire 8 $ d6_o [7:0] $end
$var wire 8 % d5_o [7:0] $end
$var wire 8 & d4_o [7:0] $end
$var wire 8 ' d3_o [7:0] $end
$var wire 8 ( d2_o [7:0] $end
$var wire 8 ) d1_o [7:0] $end
$var wire 8 * d0_o [7:0] $end
$var reg 1 + clk $end
$var reg 1 , done_i $end
$var reg 8 - grayscale_i [7:0] $end
$var reg 1 . rst $end
$var integer 32 / i [31:0] $end
$scope module SOBEL_DATA_BUFFER $end
$var wire 1 + clk $end
$var wire 1 , done_i $end
$var wire 8 0 grayscale_i [7:0] $end
$var wire 1 . rst $end
$var wire 1 1 double_line_buffer_done $end
$var wire 8 2 double_line_buffer_data2 [7:0] $end
$var wire 8 3 double_line_buffer_data1 [7:0] $end
$var wire 8 4 double_line_buffer_data0 [7:0] $end
$var wire 1 ! done_o $end
$var wire 8 5 d8_o [7:0] $end
$var wire 8 6 d7_o [7:0] $end
$var wire 8 7 d6_o [7:0] $end
$var wire 8 8 d5_o [7:0] $end
$var wire 8 9 d4_o [7:0] $end
$var wire 8 : d3_o [7:0] $end
$var wire 8 ; d2_o [7:0] $end
$var wire 8 < d1_o [7:0] $end
$var wire 8 = d0_o [7:0] $end
$scope module FIFO_DOUBLE_LINE_BUFFER $end
$var wire 1 + clk $end
$var wire 8 > data0_o [7:0] $end
$var wire 8 ? data1_o [7:0] $end
$var wire 8 @ data2_o [7:0] $end
$var wire 8 A data_i [7:0] $end
$var wire 1 1 done_o $end
$var wire 1 . rst $end
$var wire 1 , we_i $end
$var wire 1 B fifo2_done $end
$var wire 8 C fifo2_data [7:0] $end
$var wire 1 D fifo1_done $end
$var wire 8 E fifo1_data [7:0] $end
$scope module FIFO_SINGLE_LINE_BUFFER_01 $end
$var wire 1 + clk $end
$var wire 8 F data_i [7:0] $end
$var wire 8 G data_o [7:0] $end
$var wire 1 . rst $end
$var wire 1 , we_i $end
$var wire 1 D done_o $end
$var parameter 32 H DEPTH $end
$var reg 10 I iCounter [9:0] $end
$var reg 10 J rd_pointer [9:0] $end
$var reg 10 K wr_pointer [9:0] $end
$upscope $end
$scope module FIFO_SINGLE_LINE_BUFFER_02 $end
$var wire 1 + clk $end
$var wire 8 L data_i [7:0] $end
$var wire 8 M data_o [7:0] $end
$var wire 1 . rst $end
$var wire 1 D we_i $end
$var wire 1 B done_o $end
$var parameter 32 N DEPTH $end
$var reg 10 O iCounter [9:0] $end
$var reg 10 P rd_pointer [9:0] $end
$var reg 10 Q wr_pointer [9:0] $end
$upscope $end
$upscope $end
$scope module SOBEL_DATA_MODULATE $end
$var wire 1 + clk $end
$var wire 8 R d0_i [7:0] $end
$var wire 8 S d1_i [7:0] $end
$var wire 8 T d2_i [7:0] $end
$var wire 1 1 done_i $end
$var wire 1 . rst $end
$var wire 1 ! done_o $end
$var parameter 32 U COLS $end
$var parameter 32 V ROWS $end
$var reg 8 W d0_o [7:0] $end
$var reg 8 X d1_o [7:0] $end
$var reg 8 Y d2_o [7:0] $end
$var reg 8 Z d3_o [7:0] $end
$var reg 8 [ d4_o [7:0] $end
$var reg 8 \ d5_o [7:0] $end
$var reg 8 ] d6_o [7:0] $end
$var reg 8 ^ d7_o [7:0] $end
$var reg 8 _ d8_o [7:0] $end
$var reg 8 ` data0 [7:0] $end
$var reg 8 a data1 [7:0] $end
$var reg 8 b data2 [7:0] $end
$var reg 8 c data3 [7:0] $end
$var reg 8 d data4 [7:0] $end
$var reg 8 e data5 [7:0] $end
$var reg 8 f data6 [7:0] $end
$var reg 8 g data7 [7:0] $end
$var reg 8 h data8 [7:0] $end
$var reg 10 i iCols [9:0] $end
$var reg 8 j iCounter [7:0] $end
$var reg 10 k iRows [9:0] $end
$upscope $end
$upscope $end
$upscope $end
$enddefinitions $end
$comment Show the parameter values. $end
$dumpall
b101 V
b110 U
b110 N
b110 H
$end
#0
$dumpvars
b0 k
b0 j
b0 i
b0 h
b0 g
b0 f
b0 e
b0 d
b0 c
b0 b
b0 a
b0 `
b0 _
b0 ^
b0 ]
b0 \
b0 [
b0 Z
b0 Y
b0 X
b0 W
bx T
bx S
b0 R
b0 Q
b0 P
b0 O
bx M
bx L
b0 K
b0 J
b0 I
bx G
b0 F
bx E
0D
bx C
0B
b0 A
bx @
bx ?
b0 >
b0 =
b0 <
b0 ;
b0 :
b0 9
b0 8
b0 7
b0 6
b0 5
b0 4
bx 3
bx 2
01
b0 0
bx /
1.
b0 -
0,
1+
b0 *
b0 )
b0 (
b0 '
b0 &
b0 %
b0 $
b0 #
b0 "
0!
$end
#5
0+
#10
b1 K
b1 3
b1 ?
b1 S
b1 E
b1 G
b1 L
b1 I
1+
b1 4
b1 >
b1 R
b1 -
b1 0
b1 A
b1 F
b1 /
1,
0.
#15
0+
#20
b10 I
b10 K
1+
b10 4
b10 >
b10 R
b10 -
b10 0
b10 A
b10 F
b10 /
#25
0+
#30
b11 K
b11 I
1+
b11 4
b11 >
b11 R
b11 -
b11 0
b11 A
b11 F
b11 /
#35
0+
#40
b100 I
b100 K
1+
b100 4
b100 >
b100 R
b100 -
b100 0
b100 A
b100 F
b100 /
#45
0+
#50
b101 K
b101 I
1+
b101 4
b101 >
b101 R
b101 -
b101 0
b101 A
b101 F
b101 /
#55
0+
#60
11
1D
b110 I
b0 K
1+
b110 4
b110 >
b110 R
b110 -
b110 0
b110 A
b110 F
b110 /
#65
0+
#70
b111 h
b1 e
bx b
b1 j
b1 Q
b1 2
b1 @
b1 T
b1 C
b1 M
b1 O
b1 J
b1 K
b10 3
b10 ?
b10 S
b10 E
b10 G
b10 L
1+
b111 4
b111 >
b111 R
b111 -
b111 0
b111 A
b111 F
b111 /
#75
0+
#80
b1000 "
b1000 5
b1000 _
b111 #
b111 6
b111 ^
b10 %
b10 8
b10 \
b1 &
b1 9
b1 [
1!
b10 K
b11 3
b11 ?
b11 S
b11 E
b11 G
b11 L
b10 J
b10 O
b10 Q
b10 j
b1000 h
b111 g
b10 e
b1 d
b1 b
bx a
1+
b1000 4
b1000 >
b1000 R
b1000 -
b1000 0
b1000 A
b1000 F
b1000 /
#85
0+
#90
b1001 "
b1001 5
b1001 _
b1000 #
b1000 6
b1000 ^
b111 $
b111 7
b111 ]
b11 %
b11 8
b11 \
b10 &
b10 9
b10 [
b1 '
b1 :
b1 Z
b1001 h
b1000 g
b111 f
b11 e
b10 d
b1 c
b1 a
bx `
b1 i
b11 Q
b11 O
b11 J
b11 K
b100 3
b100 ?
b100 S
b100 E
b100 G
b100 L
1+
b1001 4
b1001 >
b1001 R
b1001 -
b1001 0
b1001 A
b1001 F
b1001 /
#95
0+
#100
b1010 "
b1010 5
b1010 _
b1001 #
b1001 6
b1001 ^
b1000 $
b1000 7
b1000 ]
b100 %
b100 8
b100 \
b11 &
b11 9
b11 [
b10 '
b10 :
b10 Z
b100 K
b101 3
b101 ?
b101 S
b101 E
b101 G
b101 L
b100 J
b100 O
b100 Q
b10 i
b1010 h
b1001 g
b1000 f
b100 e
b11 d
b10 c
b1 `
1+
b1010 4
b1010 >
b1010 R
b1010 -
b1010 0
b1010 A
b1010 F
b1010 /
#105
0+
#110
b1011 "
b1011 5
b1011 _
b1010 #
b1010 6
b1010 ^
b1001 $
b1001 7
b1001 ]
b101 %
b101 8
b101 \
b100 &
b100 9
b100 [
b11 '
b11 :
b11 Z
b1011 h
b1010 g
b1001 f
b101 e
b100 d
b11 c
b11 i
b101 Q
b101 O
b101 J
b101 K
b110 3
b110 ?
b110 S
b110 E
b110 G
b110 L
1+
b1011 4
b1011 >
b1011 R
b1011 -
b1011 0
b1011 A
b1011 F
b1011 /
#115
0+
#120
1B
b1100 "
b1100 5
b1100 _
b1011 #
b1011 6
b1011 ^
b1010 $
b1010 7
b1010 ]
b110 %
b110 8
b110 \
b101 &
b101 9
b101 [
b100 '
b100 :
b100 Z
b0 K
b111 3
b111 ?
b111 S
b111 E
b111 G
b111 L
b0 J
b110 O
b0 Q
b100 i
b1100 h
b1011 g
b1010 f
b110 e
b101 d
b100 c
1+
b1100 4
b1100 >
b1100 R
b1100 -
b1100 0
b1100 A
b1100 F
b1100 /
#125
0+
#130
b0 "
b0 5
b0 _
b1100 #
b1100 6
b1100 ^
b1011 $
b1011 7
b1011 ]
b0 %
b0 8
b0 \
b110 &
b110 9
b110 [
b101 '
b101 :
b101 Z
b1101 h
b1100 g
b1011 f
b111 e
b110 d
b101 c
b101 i
b1 P
b1 Q
b10 2
b10 @
b10 T
b10 C
b10 M
b1 J
b1 K
b1000 3
b1000 ?
b1000 S
b1000 E
b1000 G
b1000 L
1+
b1101 4
b1101 >
b1101 R
b1101 -
b1101 0
b1101 A
b1101 F
b1101 /
#135
0+
#140
b1110 "
b1110 5
b1110 _
b1101 #
b1101 6
b1101 ^
b0 $
b0 7
b0 ]
b1000 %
b1000 8
b1000 \
b111 &
b111 9
b111 [
b0 '
b0 :
b0 Z
b10 (
b10 ;
b10 Y
b1 )
b1 <
b1 X
b10 K
b1001 3
b1001 ?
b1001 S
b1001 E
b1001 G
b1001 L
b10 J
b10 Q
b11 2
b11 @
b11 T
b11 C
b11 M
b10 P
b1 k
b0 i
b1110 h
b1101 g
b1100 f
b1000 e
b111 d
b110 c
b10 b
1+
b1110 4
b1110 >
b1110 R
b1110 -
b1110 0
b1110 A
b1110 F
b1110 /
#145
0+
#150
b1111 "
b1111 5
b1111 _
b1110 #
b1110 6
b1110 ^
b1101 $
b1101 7
b1101 ]
b1001 %
b1001 8
b1001 \
b1000 &
b1000 9
b1000 [
b111 '
b111 :
b111 Z
b11 (
b11 ;
b11 Y
b10 )
b10 <
b10 X
b1 *
b1 =
b1 W
b1111 h
b1110 g
b1101 f
b1001 e
b1000 d
b111 c
b11 b
b10 a
b1 i
b11 P
b11 Q
b100 2
b100 @
b100 T
b100 C
b100 M
b11 J
b11 K
b1010 3
b1010 ?
b1010 S
b1010 E
b1010 G
b1010 L
1+
b1111 4
b1111 >
b1111 R
b1111 -
b1111 0
b1111 A
b1111 F
b1111 /
#155
0+
#160
b10000 "
b10000 5
b10000 _
b1111 #
b1111 6
b1111 ^
b1110 $
b1110 7
b1110 ]
b1010 %
b1010 8
b1010 \
b1001 &
b1001 9
b1001 [
b1000 '
b1000 :
b1000 Z
b100 (
b100 ;
b100 Y
b11 )
b11 <
b11 X
b10 *
b10 =
b10 W
b100 K
b1011 3
b1011 ?
b1011 S
b1011 E
b1011 G
b1011 L
b100 J
b100 Q
b101 2
b101 @
b101 T
b101 C
b101 M
b100 P
b10 i
b10000 h
b1111 g
b1110 f
b1010 e
b1001 d
b1000 c
b100 b
b11 a
b10 `
1+
b10000 4
b10000 >
b10000 R
b10000 -
b10000 0
b10000 A
b10000 F
b10000 /
#165
0+
#170
b10001 "
b10001 5
b10001 _
b10000 #
b10000 6
b10000 ^
b1111 $
b1111 7
b1111 ]
b1011 %
b1011 8
b1011 \
b1010 &
b1010 9
b1010 [
b1001 '
b1001 :
b1001 Z
b101 (
b101 ;
b101 Y
b100 )
b100 <
b100 X
b11 *
b11 =
b11 W
b10001 h
b10000 g
b1111 f
b1011 e
b1010 d
b1001 c
b101 b
b100 a
b11 `
b11 i
b101 P
b101 Q
b110 2
b110 @
b110 T
b110 C
b110 M
b101 J
b101 K
b1100 3
b1100 ?
b1100 S
b1100 E
b1100 G
b1100 L
1+
b10001 4
b10001 >
b10001 R
b10001 -
b10001 0
b10001 A
b10001 F
b10001 /
#175
0+
#180
b10010 "
b10010 5
b10010 _
b10001 #
b10001 6
b10001 ^
b10000 $
b10000 7
b10000 ]
b1100 %
b1100 8
b1100 \
b1011 &
b1011 9
b1011 [
b1010 '
b1010 :
b1010 Z
b110 (
b110 ;
b110 Y
b101 )
b101 <
b101 X
b100 *
b100 =
b100 W
b0 K
b1101 3
b1101 ?
b1101 S
b1101 E
b1101 G
b1101 L
b0 J
b0 Q
b111 2
b111 @
b111 T
b111 C
b111 M
b0 P
b100 i
b10010 h
b10001 g
b10000 f
b1100 e
b1011 d
b1010 c
b110 b
b101 a
b100 `
1+
b10010 4
b10010 >
b10010 R
b10010 -
b10010 0
b10010 A
b10010 F
b10010 /
#185
0+
#190
b0 "
b0 5
b0 _
b10010 #
b10010 6
b10010 ^
b10001 $
b10001 7
b10001 ]
b0 %
b0 8
b0 \
b1100 &
b1100 9
b1100 [
b1011 '
b1011 :
b1011 Z
b0 (
b0 ;
b0 Y
b110 )
b110 <
b110 X
b101 *
b101 =
b101 W
b10011 h
b10010 g
b10001 f
b1101 e
b1100 d
b1011 c
b111 b
b110 a
b101 `
b101 i
b1 P
b1 Q
b1000 2
b1000 @
b1000 T
b1000 C
b1000 M
b1 J
b1 K
b1110 3
b1110 ?
b1110 S
b1110 E
b1110 G
b1110 L
1+
b10011 4
b10011 >
b10011 R
b10011 -
b10011 0
b10011 A
b10011 F
b10011 /
#195
0+
#200
b10100 "
b10100 5
b10100 _
b10011 #
b10011 6
b10011 ^
b0 $
b0 7
b0 ]
b1110 %
b1110 8
b1110 \
b1101 &
b1101 9
b1101 [
b0 '
b0 :
b0 Z
b1000 (
b1000 ;
b1000 Y
b111 )
b111 <
b111 X
b0 *
b0 =
b0 W
b10 K
b1111 3
b1111 ?
b1111 S
b1111 E
b1111 G
b1111 L
b10 J
b10 Q
b1001 2
b1001 @
b1001 T
b1001 C
b1001 M
b10 P
b10 k
b0 i
b10100 h
b10011 g
b10010 f
b1110 e
b1101 d
b1100 c
b1000 b
b111 a
b110 `
1+
b10100 4
b10100 >
b10100 R
b10100 -
b10100 0
b10100 A
b10100 F
b10100 /
#205
0+
#210
b10101 "
b10101 5
b10101 _
b10100 #
b10100 6
b10100 ^
b10011 $
b10011 7
b10011 ]
b1111 %
b1111 8
b1111 \
b1110 &
b1110 9
b1110 [
b1101 '
b1101 :
b1101 Z
b1001 (
b1001 ;
b1001 Y
b1000 )
b1000 <
b1000 X
b111 *
b111 =
b111 W
b10101 h
b10100 g
b10011 f
b1111 e
b1110 d
b1101 c
b1001 b
b1000 a
b111 `
b1 i
b11 P
b11 Q
b1010 2
b1010 @
b1010 T
b1010 C
b1010 M
b11 J
b11 K
b10000 3
b10000 ?
b10000 S
b10000 E
b10000 G
b10000 L
1+
b10101 4
b10101 >
b10101 R
b10101 -
b10101 0
b10101 A
b10101 F
b10101 /
#215
0+
#220
b10110 "
b10110 5
b10110 _
b10101 #
b10101 6
b10101 ^
b10100 $
b10100 7
b10100 ]
b10000 %
b10000 8
b10000 \
b1111 &
b1111 9
b1111 [
b1110 '
b1110 :
b1110 Z
b1010 (
b1010 ;
b1010 Y
b1001 )
b1001 <
b1001 X
b1000 *
b1000 =
b1000 W
b100 K
b10001 3
b10001 ?
b10001 S
b10001 E
b10001 G
b10001 L
b100 J
b100 Q
b1011 2
b1011 @
b1011 T
b1011 C
b1011 M
b100 P
b10 i
b10110 h
b10101 g
b10100 f
b10000 e
b1111 d
b1110 c
b1010 b
b1001 a
b1000 `
1+
b10110 4
b10110 >
b10110 R
b10110 -
b10110 0
b10110 A
b10110 F
b10110 /
#225
0+
#230
b10111 "
b10111 5
b10111 _
b10110 #
b10110 6
b10110 ^
b10101 $
b10101 7
b10101 ]
b10001 %
b10001 8
b10001 \
b10000 &
b10000 9
b10000 [
b1111 '
b1111 :
b1111 Z
b1011 (
b1011 ;
b1011 Y
b1010 )
b1010 <
b1010 X
b1001 *
b1001 =
b1001 W
b10111 h
b10110 g
b10101 f
b10001 e
b10000 d
b1111 c
b1011 b
b1010 a
b1001 `
b11 i
b101 P
b101 Q
b1100 2
b1100 @
b1100 T
b1100 C
b1100 M
b101 J
b101 K
b10010 3
b10010 ?
b10010 S
b10010 E
b10010 G
b10010 L
1+
b10111 4
b10111 >
b10111 R
b10111 -
b10111 0
b10111 A
b10111 F
b10111 /
#235
0+
#240
b11000 "
b11000 5
b11000 _
b10111 #
b10111 6
b10111 ^
b10110 $
b10110 7
b10110 ]
b10010 %
b10010 8
b10010 \
b10001 &
b10001 9
b10001 [
b10000 '
b10000 :
b10000 Z
b1100 (
b1100 ;
b1100 Y
b1011 )
b1011 <
b1011 X
b1010 *
b1010 =
b1010 W
b0 K
b10011 3
b10011 ?
b10011 S
b10011 E
b10011 G
b10011 L
b0 J
b0 Q
b1101 2
b1101 @
b1101 T
b1101 C
b1101 M
b0 P
b100 i
b11000 h
b10111 g
b10110 f
b10010 e
b10001 d
b10000 c
b1100 b
b1011 a
b1010 `
1+
b11000 4
b11000 >
b11000 R
b11000 -
b11000 0
b11000 A
b11000 F
b11000 /
#245
0+
#250
b0 "
b0 5
b0 _
b11000 #
b11000 6
b11000 ^
b10111 $
b10111 7
b10111 ]
b0 %
b0 8
b0 \
b10010 &
b10010 9
b10010 [
b10001 '
b10001 :
b10001 Z
b0 (
b0 ;
b0 Y
b1100 )
b1100 <
b1100 X
b1011 *
b1011 =
b1011 W
b11001 h
b11000 g
b10111 f
b10011 e
b10010 d
b10001 c
b1101 b
b1100 a
b1011 `
b101 i
b1 P
b1 Q
b1110 2
b1110 @
b1110 T
b1110 C
b1110 M
b1 J
b1 K
b10100 3
b10100 ?
b10100 S
b10100 E
b10100 G
b10100 L
1+
b11001 4
b11001 >
b11001 R
b11001 -
b11001 0
b11001 A
b11001 F
b11001 /
#255
0+
#260
b11010 "
b11010 5
b11010 _
b11001 #
b11001 6
b11001 ^
b0 $
b0 7
b0 ]
b10100 %
b10100 8
b10100 \
b10011 &
b10011 9
b10011 [
b0 '
b0 :
b0 Z
b1110 (
b1110 ;
b1110 Y
b1101 )
b1101 <
b1101 X
b0 *
b0 =
b0 W
b10 K
b10101 3
b10101 ?
b10101 S
b10101 E
b10101 G
b10101 L
b10 J
b10 Q
b1111 2
b1111 @
b1111 T
b1111 C
b1111 M
b10 P
b11 k
b0 i
b11010 h
b11001 g
b11000 f
b10100 e
b10011 d
b10010 c
b1110 b
b1101 a
b1100 `
1+
b11010 4
b11010 >
b11010 R
b11010 -
b11010 0
b11010 A
b11010 F
b11010 /
#265
0+
