grayscale_to_rgb/grayscale_to_rgb.v
`timescale 1ps/1ps

module grayscale_to_rgb (

    input clk,
    input rst,

    input [7:0] grayscale_i,
    input done_i,

    output reg [7:0] red_o,
    output reg [7:0] green_o,
    output reg [7:0] blue_o,

    output reg done_o
);

always @(posedge clk) begin
    if(rst) begin
        red_o <= 8'b0;
        green_o <= 8'b0;
        blue_o <= 8'b0;
        done_o <= 8'b0;
    end else begin
        if(done_i) begin
            red_o <= grayscale_i;
            green_o <= grayscale_i;
            blue_o <= grayscale_i;
        end

        done_o <= done_i;
    end
end

endmodule

grayscale_to_rgb/grayscale_to_rgb_tb.sv
`include "grayscale_to_rgb.v"
`define clk_period  10

module grayscale_to_rgb_tb();

reg clk, rst;
reg [7:0] grayscale_i;
reg done_i;

wire [7:0] red_o, green_o, blue_o;
wire done_o;

grayscale_to_rgb GRAYSCALE_TO_RGB(

    .clk(clk),
    .rst(rst),

    .grayscale_i(grayscale_i),
    .done_i(done_i),

    .red_o(red_o),
    .green_o(green_o),
    .blue_o(blue_o),

    .done_o(done_o)
);

initial clk = 1'b1;
always #(`clk_period / 2) clk = ~clk;

integer i;

initial begin
    rst = 1'b1;
    done_i = 1'b0;
    grayscale_i = 8'b0;

    $dumpfile("waveforms/grayscale_to_rgb_tb.vcd");
    $dumpvars(0, grayscale_to_rgb_tb);

    #(`clk_period);
    rst = 1'b0;
    done_i = 1'b1;

    for(i = 0; i < 9; i = i + 1) begin
        grayscale_i = i + 1;
        #(`clk_period);
    end

    #(`clk_period);
    done_i = 1'b0;
    #(`clk_period);
    
    $stop;
end


endmodule

grayscale_to_rgb/waveforms/grayscale_to_rgb_tb.vcd
$date
	Mon Mar 17 23:12:26 2025
$end
$version
	Icarus Verilog
$end
$timescale
	1ps
$end
$scope module grayscale_to_rgb_tb $end
$var wire 8 ! red_o [7:0] $end
$var wire 8 " green_o [7:0] $end
$var wire 1 # done_o $end
$var wire 8 $ blue_o [7:0] $end
$var reg 1 % clk $end
$var reg 1 & done_i $end
$var reg 8 ' grayscale_i [7:0] $end
$var reg 1 ( rst $end
$var integer 32 ) i [31:0] $end
$scope module GRAYSCALE_TO_RGB $end
$var wire 1 % clk $end
$var wire 1 & done_i $end
$var wire 8 * grayscale_i [7:0] $end
$var wire 1 ( rst $end
$var reg 8 + blue_o [7:0] $end
$var reg 1 # done_o $end
$var reg 8 , green_o [7:0] $end
$var reg 8 - red_o [7:0] $end
$upscope $end
$upscope $end
$enddefinitions $end
$comment Show the parameter values. $end
$dumpall
$end
#0
$dumpvars
b0 -
b0 ,
b0 +
b0 *
bx )
1(
b0 '
0&
1%
b0 $
0#
b0 "
b0 !
$end
#5
0%
#10
1#
b1 $
b1 +
b1 "
b1 ,
b1 !
b1 -
1%
b1 '
b1 *
b0 )
1&
0(
#15
0%
#20
b10 $
b10 +
b10 "
b10 ,
b10 !
b10 -
1%
b10 '
b10 *
b1 )
#25
0%
#30
b11 $
b11 +
b11 "
b11 ,
b11 !
b11 -
1%
b11 '
b11 *
b10 )
#35
0%
#40
b100 $
b100 +
b100 "
b100 ,
b100 !
b100 -
1%
b100 '
b100 *
b11 )
#45
0%
#50
b101 $
b101 +
b101 "
b101 ,
b101 !
b101 -
1%
b101 '
b101 *
b100 )
#55
0%
#60
b110 $
b110 +
b110 "
b110 ,
b110 !
b110 -
1%
b110 '
b110 *
b101 )
#65
0%
#70
b111 $
b111 +
b111 "
b111 ,
b111 !
b111 -
1%
b111 '
b111 *
b110 )
#75
0%
#80
b1000 $
b1000 +
b1000 "
b1000 ,
b1000 !
b1000 -
1%
b1000 '
b1000 *
b111 )
#85
0%
#90
b1001 $
b1001 +
b1001 "
b1001 ,
b1001 !
b1001 -
1%
b1001 '
b1001 *
b1000 )
#95
0%
#100
1%
b1001 )
#105
0%
#110
0#
1%
0&
