fifo_single_line_buffer/fifo_single_line_buffer.v
`timescale 1ps/1ps

// The implementation for a single buffer such as fifo Line buffer 1
// if there is continuous data stream filling the fifo, then once the fifo
// is full the fifo data will be read continuously, while the input data
// continue writing to the fifo. --> This is effectively shifting data out
// from the fifo while new data is shifting into the fifo.
module fifo_single_line_buffer (
    input clk,
    input rst,
    input we_i,

    input [7:0] data_i,
    output [7:0] data_o,
    output done_o
);
    // This suggests that the buffer is designed to hold 640 pixel values 
    // (often corresponding to the width of an image in a row). 
    // parameter DEPTH = 640;
    parameter DEPTH = 5; // for sim
    reg [7:0] mem [DEPTH - 1: 0];

    reg [9:0] wr_pointer; // we need 10 bits because we need 10 bits to cover 640
    reg [9:0] rd_pointer;
    //  A 10-bit counter used to track how many pixels have been written into the FIFO buffer. 
    // When it reaches DEPTH, it indicates that the FIFO is full.
    reg [9:0] iCounter;
    // This output signal indicates whether the FIFO has been filled with data or not. 
    assign done_o = (iCounter == DEPTH) ? 1'b1 : 1'b0;
    assign data_o = mem[rd_pointer];

    //------------------- Handle with iCounter --------------------
    // we can see that the iCounter is used to determine when the FIFO is full.
    always @(posedge clk) begin
        if(rst) begin
            iCounter <= 10'b0;
        end else begin
            if(we_i == 1'b1) begin
                iCounter <= (iCounter == DEPTH ) ? iCounter : iCounter + 10'b1;
            end
        end
    end

    //------------------- Handle with write process --------------------
    always @(posedge clk) begin
        if(rst) begin
            wr_pointer <= 10'b0;
        end else begin
            if(we_i == 1'b1) begin
                mem[wr_pointer] <= data_i;
                wr_pointer <= (wr_pointer == DEPTH - 1) ? 0 : wr_pointer + 10'b1;
            end
        end
    end

    //------------------- Handle with read process --------------------
    always @(posedge clk) begin
        if(rst) begin
            rd_pointer <= 10'b0;
        end else begin
            // The read pointer is updated after each read once the buffer has been filled.
            if(iCounter == DEPTH) begin
                rd_pointer <= (rd_pointer == DEPTH - 1) ? 0 : rd_pointer + 10'b1;
            end
        end
    end

endmodule

fifo_single_line_buffer/fifo_single_line_buffer_tb.v
`include "fifo_single_line_buffer.v"

`define clk_period  10

module fifo_single_line_buffer_tb();

reg clk, rst;
reg [7:0] data_i;
reg we_i;
wire [7:0] data_o;
wire done_o;

fifo_single_line_buffer FIFO_SINGLE_LINE_BUFFER (
    .clk(clk),
    .rst(rst),
    .we_i(we_i),

    .data_i(data_i),
    .data_o(data_o),
    .done_o(done_o)
);

initial clk = 1'b1;
always #(`clk_period / 2) clk = ~clk;
integer i;

initial begin
    rst = 1'b1;
    data_i = 8'b0;
    we_i = 1'b0;

    $dumpfile("waveforms/fifo_single_line_buffer.vcd");
    $dumpvars(0, fifo_single_line_buffer_tb);

    #(`clk_period);
    rst = 1'b0;
    we_i = 1'b1;

    for(i = 1; i < 11; i = i + 1) begin
        data_i = i;
        #(`clk_period);
    end

    #(`clk_period);
    we_i = 1'b0;

    $stop;
end

endmodule

fifo_single_line_buffer/waveforms/fifo_single_line_buffer.vcd
$date
	Tue Mar 11 21:17:20 2025
$end
$version
	Icarus Verilog
$end
$timescale
	1ps
$end
$scope module fifo_single_line_buffer_tb $end
$var wire 1 ! done_o $end
$var wire 8 " data_o [7:0] $end
$var reg 1 # clk $end
$var reg 8 $ data_i [7:0] $end
$var reg 1 % rst $end
$var reg 1 & we_i $end
$var integer 32 ' i [31:0] $end
$scope module FIFO_SINGLE_LINE_BUFFER $end
$var wire 1 # clk $end
$var wire 8 ( data_i [7:0] $end
$var wire 8 ) data_o [7:0] $end
$var wire 1 % rst $end
$var wire 1 & we_i $end
$var wire 1 ! done_o $end
$var parameter 32 * DEPTH $end
$var reg 10 + iCounter [9:0] $end
$var reg 10 , rd_pointer [9:0] $end
$var reg 10 - wr_pointer [9:0] $end
$upscope $end
$upscope $end
$enddefinitions $end
$comment Show the parameter values. $end
$dumpall
b101 *
$end
#0
$dumpvars
b0 -
b0 ,
b0 +
bx )
b0 (
bx '
0&
1%
b0 $
1#
bx "
0!
$end
#5
0#
#10
b1 -
b1 "
b1 )
b1 +
1#
b1 $
b1 (
b1 '
1&
0%
#15
0#
#20
b10 +
b10 -
1#
b10 $
b10 (
b10 '
#25
0#
#30
b11 -
b11 +
1#
b11 $
b11 (
b11 '
#35
0#
#40
b100 +
b100 -
1#
b100 $
b100 (
b100 '
#45
0#
#50
1!
b0 -
b101 +
1#
b101 $
b101 (
b101 '
#55
0#
#60
b1 -
b10 "
b10 )
b1 ,
1#
b110 $
b110 (
b110 '
#65
0#
#70
b10 ,
b10 -
b11 "
b11 )
1#
b111 $
b111 (
b111 '
#75
0#
#80
b11 -
b100 "
b100 )
b11 ,
1#
b1000 $
b1000 (
b1000 '
#85
0#
#90
b100 ,
b100 -
b101 "
b101 )
1#
b1001 $
b1001 (
b1001 '
#95
0#
#100
b0 -
b110 "
b110 )
b0 ,
1#
b1010 $
b1010 (
b1010 '
#105
0#
#110
b1 ,
b1 -
b111 "
b111 )
1#
b1011 '
