rgb_to_grayscale/store_grayscale.v
`timescale 1ps/1ps

module store_grayscale 
#(parameter RESULT_ARRAY_LEN = 50 * 1024)
(
    input clk,
    input rst,
    input done_o,
    input [7:0] grayscale_o,
    output reg [7:0] result[RESULT_ARRAY_LEN-1:0]
);

integer  j;
always @(posedge clk) begin
    if(rst == 1'b1) begin
        j <= 0;
    end else begin
        if (done_o == 1'b1) begin
            result[j] <= grayscale_o;
            result[j+1] <= grayscale_o;
            result[j+2] <= grayscale_o;
            j <= j + 3;
        end
    end
end

endmodule

rgb_to_grayscale/rgb_to_grayscale.v
`timescale 1ps/1ps

module rgb_to_grayscale(

    input clk,
    input rst,

    input [7:0] red_i,
    input [7:0] green_i,
    input [7:0] blue_i,

    input cam_done_i,

    output reg [7:0] grayscale_o,
    output reg done_o
);

reg [15:0] count;

    always @(posedge clk) begin
        if(rst) begin
            count <= 12'b0;
            done_o <= 1'b0;
            grayscale_o <= 7'b0;
        end else begin
            count <= count + 1;
            if(cam_done_i == 1'b1) begin
                grayscale_o <= (red_i >> 2) + (red_i >> 5) + 
                                (green_i >> 1) + (green_i >> 4) +
                                (blue_i >> 4) + (blue_i >> 5);
                done_o <= 1'b1;
            end else begin
                grayscale_o <= 8'b0;
                done_o <= 1'b0;
                count <= 12'b0;
            end
        end
    end

endmodule

rgb_to_grayscale/rgb_to_grayscale_tb.sv
`define clk_period  10
`include "rgb_to_grayscale.v"
`include "store_grayscale.v"

module rgb_to_grayscale_tb ();

reg clk,rst;
reg [7:0] red_i, green_i, blue_i;
reg done_i;
wire [7:0] grayscale_o;
wire done_o;

rgb_to_grayscale RGB_TO_GRAYSCALE(
    .clk(clk),
    .rst(rst),
    .red_i(red_i),
    .green_i(green_i),
    .blue_i(blue_i),
    .cam_done_i(done_i),
    .grayscale_o(grayscale_o),
    .done_o(done_o)
);

initial clk = 1'b1;
always #(`clk_period / 2) clk = ~clk;

//-------------------------------------------------------------
localparam RESULT_ARRAY_LEN = 50 * 1024; // 50 KB
reg [7:0] result[RESULT_ARRAY_LEN-1:0];

store_grayscale STORE_GRAYSCALE(
    clk,
    rst,
    done_o,
    grayscale_o,
    result
);

//-------------------------------------------------------------

// 128x128 RGB image with pixel size being 24 bits
`define read_file_name "input.bmp"
localparam BMP_ARRAY_LEN = 50 * 1024; // 50 KB

reg [7:0] bmp_data[BMP_ARRAY_LEN-1: 0];
integer bmp_size, bmp_start_pos, bmp_width, bmp_height, bit_count;
integer read_count;

task readBMP;
    integer fileId;
    integer i;
    begin
        fileId = $fopen(`read_file_name, "rb");
        if(fileId == 0) begin
            $display("Open BMP error\n");
            $finish;
        end else begin
            read_count = $fread(bmp_data, fileId);
            if(read_count < 0) begin
                $display("Failed to read %s\n", `read_file_name);
                $finish;
            end
            $fclose(fileId);

            // extract fields from bmp_data
            bmp_size = {bmp_data[5], bmp_data[4], bmp_data[3], bmp_data[2]};
            $display("bmp_size = %d\n", bmp_size);

            bmp_start_pos = {bmp_data[13], bmp_data[12], bmp_data[11], bmp_data[10]};
            $display("bmp_start_pos = %d\n", bmp_start_pos);

            bmp_width = {bmp_data[21], bmp_data[20], bmp_data[19], bmp_data[18]};
            $display("bmp_width = %d\n", bmp_width);

            bmp_height = {bmp_data[25], bmp_data[24], bmp_data[23], bmp_data[22]};
            $display("bmp_height = %d\n", bmp_height);

            bit_count = {bmp_data[29], bmp_data[28]};
            $display("bit_count = %d\n", bit_count);

            if(bit_count != 24) begin
                $display("bit_count needs to be 24 !\n");
                $finish;
            end

            // this is the case where we need to pad zeros
            if(bmp_width % 4 == 1) begin
                $display("bmp_width mod 4 needs to be zero\n");
                $finish;
            end

            // for(i = bmp_start_pos; i <bmp_size; i = i + 1) begin
            //     $display("%h", bmp_data[i]);
            // end
        end
    end
endtask


//-------------------------------------------------------------
`define write_file_name "result.bmp"
task writeBMP();
    integer fileId, i;
    begin
        fileId = $fopen(`write_file_name, "wb");
        if(fileId == 0) begin
            $display("Open BMP error\n");
            $finish;
        end

        for(i = 0; i < bmp_size; i = i + 1) begin
            $fwrite(fileId, "%c", bmp_data[i]);
        end

        $fclose(fileId);
        $display("writeBMP completed\n");
    end
endtask

task writeBMPFromGrayscale();
    integer fileId, i;
    begin
        fileId = $fopen(`write_file_name, "wb");
        if(fileId == 0) begin
            $display("Open BMP error\n");
            $finish;
        end

        // write the BMP file header
        for(i = 0; i < bmp_start_pos; i = i + 1) begin
            $fwrite(fileId, "%c", bmp_data[i]);
        end

        // for(i = bmp_start_pos; i <bmp_size; i = i + 1) begin
        //     $display("%h", result[i]);
        // end

        // write the BMP file content
        for(i = bmp_start_pos; i < bmp_size; i = i + 1) begin
            $fwrite(fileId, "%c", result[i - bmp_start_pos]);
        end

        $fclose(fileId);
        $display("writeBMPFromGrayscale completed\n");
    end
endtask

//-------------------------------------------------------------
integer i;
initial begin
    rst = 1'b1;
    done_i = 1'b0;

    red_i = 8'b0;
    green_i = 8'b0;
    blue_i = 8'b0;

    $dumpfile("waveforms/rgb_to_grayscale.vcd");
    $dumpvars(0, rgb_to_grayscale_tb);

    readBMP;

    #(`clk_period);
    rst = 1'b0;

    for(i = bmp_start_pos; i < bmp_size; i = i + 3) begin
        red_i = bmp_data[i+2];
        green_i = bmp_data[i+1];
        blue_i = bmp_data[i];

        #(`clk_period);
        done_i = 1'b1;
    end

    #(`clk_period);
    done_i = 1'b0;

    #(`clk_period);
    writeBMPFromGrayscale;

    #(`clk_period);
    $finish;
end

// initial begin
//     rst = 1'b1;
//     done_i = 1'b0;

//     red_i = 8'b0;
//     green_i = 8'b0;
//     blue_i = 8'b0;

//     #(`clk_period);
//     rst = 1'b0;

//     red_i = 8'b0000_0100;
//     green_i = 8'b0000_0010;
//     blue_i = 8'b0001_0000;

//     done_i = 1'b1;

//     #(`clk_period);
//     assert(done_o == 1'b1);
//     assert(grayscale_o == 8'd3);
//     $display("grayscale_o = %d\n", grayscale_o);
//     done_i = 1'b0;

//     #(`clk_period);
//     assert(done_o == 1'b0);
//     assert(grayscale_o == 8'd0);
//     readBMP;
//     writeBMP;
//     $finish;
// end
endmodule

rgb_to_grayscale/waveforms/rgb_to_grayscale.vcd
$date
	Sun Mar  9 15:57:00 2025
$end
$version
	Icarus Verilog
$end
$timescale
	1ps
$end
$scope module rgb_to_grayscale_tb $end
$var wire 8 ! grayscale_o [7:0] $end
$var wire 1 " done_o $end
$var parameter 64 # BMP_ARRAY_LEN $end
$var parameter 64 $ RESULT_ARRAY_LEN $end
$var reg 8 % blue_i [7:0] $end
$var reg 1 & clk $end
$var reg 1 ' done_i $end
$var reg 8 ( green_i [7:0] $end
$var reg 8 ) red_i [7:0] $end
$var reg 1 * rst $end
$var integer 32 + bit_count [31:0] $end
$var integer 32 , bmp_height [31:0] $end
$var integer 32 - bmp_size [31:0] $end
$var integer 32 . bmp_start_pos [31:0] $end
$var integer 32 / bmp_width [31:0] $end
$var integer 32 0 i [31:0] $end
$var integer 32 1 read_count [31:0] $end
$scope module RGB_TO_GRAYSCALE $end
$var wire 8 2 blue_i [7:0] $end
$var wire 1 ' cam_done_i $end
$var wire 1 & clk $end
$var wire 8 3 green_i [7:0] $end
$var wire 8 4 red_i [7:0] $end
$var wire 1 * rst $end
$var reg 16 5 count [15:0] $end
$var reg 1 " done_o $end
$var reg 8 6 grayscale_o [7:0] $end
$upscope $end
$scope module STORE_GRAYSCALE $end
$var wire 1 & clk $end
$var wire 1 " done_o $end
$var wire 8 7 grayscale_o [7:0] $end
$var wire 1 * rst $end
$var parameter 64 8 RESULT_ARRAY_LEN $end
$var integer 32 9 j [31:0] $end
$upscope $end
$scope task readBMP $end
$var integer 32 : fileId [31:0] $end
$upscope $end
$scope task writeBMP $end
$var integer 32 ; fileId [31:0] $end
$var integer 32 < i [31:0] $end
$upscope $end
$scope task writeBMPFromGrayscale $end
$var integer 32 = fileId [31:0] $end
$var integer 32 > i [31:0] $end
$upscope $end
$upscope $end
$enddefinitions $end
$comment Show the parameter values. $end
$dumpall
b1100100000000000 8
b1100100000000000 $
b1100100000000000 #
$end
#0
$dumpvars
bx >
bx =
bx <
bx ;
b10000000000000000000000000000011 :
b0 9
b0 7
b0 6
b0 5
b0 4
b0 3
b0 2
b1100000000110110 1
bx 0
b10000000 /
b110110 .
b1100000000110110 -
b10000000 ,
b11000 +
1*
b0 )
b0 (
0'
1&
b0 %
0"
b0 !
$end
#5
0&
#10
b0 5
1&
b1111100 %
b1111100 2
b10011010 (
b10011010 3
b1101100 )
b1101100 4
b110110 0
0*
#15
0&
#20
1"
b1111101 !
b1111101 6
b1111101 7
b1 5
1&
b1111011 %
b1111011 2
b10011011 (
b10011011 3
b1101011 )
b1101011 4
b111001 0
1'
#25
0&
#30
b11 9
b1111100 !
b1111100 6
b1111100 7
b10 5
1&
b1111001 %
b1111001 2
b10011000 (
b10011000 3
b1101001 )
b1101001 4
b111100 0
#35
0&
#40
b1111000 !
b1111000 6
b1111000 7
b11 5
b110 9
1&
b1110101 %
b1110101 2
b10010011 (
b10010011 3
b1100111 )
b1100111 4
b111111 0
#45
0&
#50
b1001 9
b1110100 !
b1110100 6
b1110100 7
b100 5
1&
b1110010 %
b1110010 2
b10001111 (
b10001111 3
b1100011 )
b1100011 4
b1000010 0
#55
0&
#60
b1101110 !
b1101110 6
b1101110 7
b101 5
b1100 9
1&
b1101110 %
b1101110 2
b10001001 (
b10001001 3
b1011110 )
b1011110 4
b1000101 0
#65
0&
#70
b1111 9
b1101100 !
b1101100 6
b1101100 7
b110 5
1&
b1101101 %
b1101101 2
b10000110 (
b10000110 3
b1011011 )
b1011011 4
b1001000 0
#75
0&
#80
b1101010 !
b1101010 6
b1101010 7
b111 5
b10010 9
1&
b1101100 %
b1101100 2
b10000010 (
b10000010 3
b1011000 )
b1011000 4
b1001011 0
#85
0&
#90
b10101 9
b1100011 !
b1100011 6
b1100011 7
b1000 5
1&
b1100110 %
b1100110 2
b1111010 (
b1111010 3
b1010001 )
b1010001 4
b1001110 0
#95
0&
#100
b1011000 !
b1011000 6
b1011000 7
b1001 5
b11000 9
1&
b1011111 %
b1011111 2
b1101110 (
b1101110 3
b1001000 )
b1001000 4
b1010001 0
#105
0&
#110
b11011 9
b1010010 !
b1010010 6
b1010010 7
b1010 5
1&
b1011101 %
b1011101 2
b1100111 (
b1100111 3
b1000011 )
b1000011 4
b1010100 0
#115
0&
#120
b1001101 !
b1001101 6
b1001101 7
b1011 5
b11110 9
1&
b1011001 %
b1011001 2
b1100001 (
b1100001 3
b111110 )
b111110 4
b1010111 0
#125
0&
#130
b100001 9
b1001001 !
b1001001 6
b1001001 7
b1100 5
1&
b1010111 %
b1010111 2
b1011101 (
b1011101 3
b111011 )
b111011 4
b1011010 0
#135
0&
#140
b1001000 !
b1001000 6
b1001000 7
b1101 5
b100100 9
1&
b1010110 %
b1010110 2
b1011010 (
b1011010 3
b111001 )
b111001 4
b1011101 0
#145
0&
#150
b100111 9
b1000101 !
b1000101 6
b1000101 7
b1110 5
1&
b1010011 %
b1010011 2
b1010110 (
b1010110 3
b110100 )
b110100 4
b1100000 0
#155
0&
#160
b111111 !
b111111 6
b111111 7
b1111 5
b101010 9
1&
b1010000 %
b1010000 2
b1001111 (
b1001111 3
b110010 )
b110010 4
b1100011 0
#165
0&
#170
b101101 9
b111010 !
b111010 6
b111010 7
b10000 5
1&
b1000111 %
b1000111 2
b1001000 (
b1001000 3
b101110 )
b101110 4
b1100110 0
#175
0&
#180
b101111 !
b101111 6
b101111 7
b10001 5
b110000 9
1&
b111001 %
b111001 2
b111100 (
b111100 3
b100111 )
b100111 4
b1101001 0
#185
0&
#190
b110011 9
b101100 !
b101100 6
b101100 7
b10010 5
1&
b110011 %
b110011 2
b110111 (
b110111 3
b100101 )
b100101 4
b1101100 0
#195
0&
#200
b101011 !
b101011 6
b101011 7
b10011 5
b110110 9
1&
b110001 %
b110001 2
b110100 (
b110100 3
b100100 )
b100100 4
b1101111 0
#205
0&
#210
b111001 9
b110011 !
b110011 6
b110011 7
b10100 5
1&
b1000000 %
b1000000 2
b111100 (
b111100 3
b101101 )
b101101 4
b1110010 0
#215
0&
#220
b111101 !
b111101 6
b111101 7
b10101 5
b111100 9
1&
b1010011 %
b1010011 2
b1000111 (
b1000111 3
b111010 )
b111010 4
b1110101 0
#225
0&
#230
b111111 9
b1000010 !
b1000010 6
b1000010 7
b10110 5
1&
b1011010 %
b1011010 2
b1001011 (
b1001011 3
b1000011 )
b1000011 4
b1111000 0
#235
0&
#240
b1001011 !
b1001011 6
b1001011 7
b10111 5
b1000010 9
1&
b1100011 %
b1100011 2
b1010001 (
b1010001 3
b1001100 )
b1001100 4
b1111011 0
#245
0&
#250
b1000101 9
b1010001 !
b1010001 6
b1010001 7
b11000 5
1&
b1101011 %
b1101011 2
b1011000 (
b1011000 3
b1010110 )
b1010110 4
b1111110 0
#255
0&
#260
b1011000 !
b1011000 6
b1011000 7
b11001 5
b1001000 9
1&
b1110011 %
b1110011 2
b1011101 (
b1011101 3
b1100000 )
b1100000 4
b10000001 0
#265
0&
#270
b1001011 9
b1100000 !
b1100000 6
b1100000 7
b11010 5
1&
b1111000 %
b1111000 2
b1100100 (
b1100100 3
b1101101 )
b1101101 4
b10000100 0
#275
0&
#280
b1100101 !
b1100101 6
b1100101 7
b11011 5
b1001110 9
1&
b1111101 %
b1111101 2
b1101010 (
b1101010 3
b1110110 )
b1110110 4
b10000111 0
#285
0&
#290
b1010001 9
b1101111 !
b1101111 6
b1101111 7
b11100 5
1&
b10000010 %
b10000010 2
b1110000 (
b1110000 3
b10000000 )
b10000000 4
b10001010 0
#295
0&
#300
b1110111 !
b1110111 6
b1110111 7
b11101 5
b1010100 9
1&
b10001010 %
b10001010 2
b1111011 (
b1111011 3
b10001110 )
b10001110 4
b10001101 0
#305
0&
#310
b1010111 9
b1111101 !
b1111101 6
b1111101 7
b11110 5
1&
b10001111 %
b10001111 2
b10000000 (
b10000000 3
b10010111 )
b10010111 4
b10010000 0
#315
0&
#320
b10000000 !
b10000000 6
b10000000 7
b11111 5
b1011010 9
1&
b10010001 %
b10010001 2
b10011100 )
b10011100 4
b10010011 0
#325
0&
#330
b1011101 9
b100000 5
1&
b10010010 %
b10010010 2
b10011111 )
b10011111 4
b10010110 0
#335
0&
#340
b10000010 !
b10000010 6
b10000010 7
b100001 5
b1100000 9
1&
b10010011 %
b10010011 2
b10100000 )
b10100000 4
b10011001 0
#345
0&
#350
b1100011 9
b10000011 !
b10000011 6
b10000011 7
b100010 5
1&
b10000011 (
b10000011 3
b10100001 )
b10100001 4
b10011100 0
#355
0&
#360
b10001100 !
b10001100 6
b10001100 7
b100011 5
b1100110 9
1&
b10011011 %
b10011011 2
b10010001 (
b10010001 3
b10100101 )
b10100101 4
b10011111 0
#365
0&
#370
b1101001 9
b10001001 !
b10001001 6
b10001001 7
b100100 5
1&
b10010100 %
b10010100 2
b10001111 (
b10001111 3
b10100000 )
b10100000 4
b10100010 0
#375
0&
#380
b10000110 !
b10000110 6
b10000110 7
b100101 5
b1101100 9
1&
b10010001 %
b10010001 2
b10001100 (
b10001100 3
b10011101 )
b10011101 4
b10100101 0
#385
0&
#390
b1101111 9
b10001001 !
b10001001 6
b10001001 7
b100110 5
1&
b10010111 %
b10010111 2
b10010000 (
b10010000 3
b10011110 )
b10011110 4
b10101000 0
#395
0&
#400
b10001111 !
b10001111 6
b10001111 7
b100111 5
b1110010 9
1&
b10011110 %
b10011110 2
b10011001 (
b10011001 3
b10100010 )
b10100010 4
b10101011 0
#405
0&
#410
b1110101 9
b10010001 !
b10010001 6
b10010001 7
b101000 5
1&
b10011010 (
b10011010 3
b10100110 )
b10100110 4
b10101110 0
#415
0&
#420
b10010010 !
b10010010 6
b10010010 7
b101001 5
b1111000 9
1&
b10011011 %
b10011011 2
b10011000 (
b10011000 3
b10101101 )
b10101101 4
b10110001 0
#425
0&
#430
b1111011 9
b10010100 !
b10010100 6
b10010100 7
b101010 5
1&
b10110101 )
b10110101 4
b10110100 0
#435
0&
#440
b10010011 !
b10010011 6
b10010011 7
b101011 5
b1111110 9
1&
b10011000 %
b10011000 2
b10010111 (
b10010111 3
b10110100 )
b10110100 4
b10110111 0
#445
0&
#450
b10000001 9
b10010100 !
b10010100 6
b10010100 7
b101100 5
1&
b10011001 %
b10011001 2
b10011000 (
b10011000 3
b10110101 )
b10110101 4
b10111010 0
#455
0&
#460
b10010110 !
b10010110 6
b10010110 7
b101101 5
b10000100 9
1&
b10011100 %
b10011100 2
b10011010 (
b10011010 3
b10111000 )
b10111000 4
b10111101 0
#465
0&
#470
b10000111 9
b101110 5
1&
b10011101 (
b10011101 3
b10110110 )
b10110110 4
b11000000 0
#475
0&
#480
b10000100 !
b10000100 6
b10000100 7
b101111 5
b10001010 9
1&
b1110101 %
b1110101 2
b10000010 (
b10000010 3
b10110010 )
b10110010 4
b11000011 0
#485
0&
#490
b10001101 9
b1011111 !
b1011111 6
b1011111 7
b110000 5
1&
b10010 %
b10010 2
b1010001 (
b1010001 3
b11000110 0
#495
0&
#500
b10000001 !
b10000001 6
b10000001 7
b110001 5
b10010000 9
1&
b11110 %
b11110 2
b10000000 (
b10000000 3
b11001001 )
b11001001 4
b11001001 0
#505
0&
#510
b10010011 9
b10001110 !
b10001110 6
b10001110 7
b110010 5
1&
b100010 %
b100010 2
b10010001 (
b10010001 3
b11010000 )
b11010000 4
b11001100 0
#515
0&
#520
b10011010 !
b10011010 6
b10011010 7
b110011 5
b10010110 9
1&
b1110000 %
b1110000 2
b10011110 (
b10011110 3
b11001001 )
b11001001 4
b11001111 0
#525
0&
#530
b10011001 9
b10010110 !
b10010110 6
b10010110 7
b110100 5
1&
b10001100 %
b10001100 2
b10011010 (
b10011010 3
b10111110 )
b10111110 4
b11010010 0
#535
0&
#540
b10010010 !
b10010010 6
b10010010 7
b110101 5
b10011100 9
1&
b10001011 %
b10001011 2
b10010100 (
b10010100 3
b10111000 )
b10111000 4
b11010101 0
#545
0&
#550
b10011111 9
b10001110 !
b10001110 6
b10001110 7
b110110 5
1&
b10000110 %
b10000110 2
b10010000 (
b10010000 3
b10110010 )
b10110010 4
b11011000 0
#555
0&
#560
b10001100 !
b10001100 6
b10001100 7
b110111 5
b10100010 9
1&
b10001000 %
b10001000 2
b10001111 (
b10001111 3
b10110000 )
b10110000 4
b11011011 0
#565
0&
#570
b10100101 9
b10001011 !
b10001011 6
b10001011 7
b111000 5
1&
b10001010 %
b10001010 2
b10001110 (
b10001110 3
b10101101 )
b10101101 4
b11011110 0
#575
0&
#580
b10001010 !
b10001010 6
b10001010 7
b111001 5
b10101000 9
1&
b10001011 %
b10001011 2
b10001111 (
b10001111 3
b10101011 )
b10101011 4
b11100001 0
#585
0&
#590
b10101011 9
b10001001 !
b10001001 6
b10001001 7
b111010 5
1&
b10001001 %
b10001001 2
b10001101 (
b10001101 3
b10101010 )
b10101010 4
b11100100 0
#595
0&
#600
b111011 5
b10101110 9
1&
b10101001 )
b10101001 4
b11100111 0
#605
0&
#610
b10110001 9
b10001011 !
b10001011 6
b10001011 7
b111100 5
1&
b10001000 %
b10001000 2
b10001111 (
b10001111 3
b10101100 )
b10101100 4
b11101010 0
#615
0&
#620
b111101 5
b10110100 9
1&
b10000111 %
b10000111 2
b11101101 0
#625
0&
#630
b10110111 9
b111110 5
1&
b10000010 %
b10000010 2
b10001110 (
b10001110 3
b10101110 )
b10101110 4
b11110000 0
#635
0&
#640
b10000100 !
b10000100 6
b10000100 7
b111111 5
b10111010 9
1&
b1001110 %
b1001110 2
b10000111 (
b10000111 3
b10111001 )
b10111001 4
b11110011 0
#645
0&
#650
b10111101 9
b10000011 !
b10000011 6
b10000011 7
b1000000 5
1&
b1010110 %
b1010110 2
b10000101 (
b10000101 3
b10110100 )
b10110100 4
b11110110 0
#655
0&
#660
b10000001 !
b10000001 6
b10000001 7
b1000001 5
b11000000 9
1&
b1110011 %
b1110011 2
b10000001 (
b10000001 3
b10101001 )
b10101001 4
b11111001 0
#665
0&
#670
b11000011 9
b10000010 !
b10000010 6
b10000010 7
b1000010 5
1&
b10000011 %
b10000011 2
b10000000 (
b10000000 3
b10100100 )
b10100100 4
b11111100 0
#675
0&
#680
b10000111 !
b10000111 6
b10000111 7
b1000011 5
b11000110 9
1&
b10010001 %
b10010001 2
b10001010 (
b10001010 3
b10100000 )
b10100000 4
b11111111 0
#685
0&
#690
b11001001 9
b10000110 !
b10000110 6
b10000110 7
b1000100 5
1&
b10001111 %
b10001111 2
b10001011 (
b10001011 3
b100000010 0
#695
0&
#700
b10000011 !
b10000011 6
b10000011 7
b1000101 5
b11001100 9
1&
b10000001 %
b10000001 2
b10000010 (
b10000010 3
b10100100 )
b10100100 4
b100000101 0
#705
0&
#710
b11001111 9
b10000100 !
b10000100 6
b10000100 7
b1000110 5
1&
b1111110 %
b1111110 2
b10000110 (
b10000110 3
b10101010 )
b10101010 4
b100001000 0
#715
0&
#720
b10001010 !
b10001010 6
b10001010 7
b1000111 5
b11010010 9
1&
b10000100 %
b10000100 2
b10001110 (
b10001110 3
b10101011 )
b10101011 4
b100001011 0
#725
0&
#730
b11010101 9
b10001001 !
b10001001 6
b10001001 7
b1001000 5
1&
b10001000 %
b10001000 2
b10001100 (
b10001100 3
b10101001 )
b10101001 4
b100001110 0
#735
0&
#740
b1001001 5
b11011000 9
1&
b10001001 %
b10001001 2
b100010001 0
#745
0&
#750
b11011011 9
b10001000 !
b10001000 6
b10001000 7
b1001010 5
1&
b10001011 (
b10001011 3
b10101000 )
b10101000 4
b100010100 0
#755
0&
#760
b10001100 !
b10001100 6
b10001100 7
b1001011 5
b11011110 9
1&
b10001010 %
b10001010 2
b10010000 (
b10010000 3
b10101010 )
b10101010 4
b100010111 0
#765
0&
#770
b11100001 9
b10010001 !
b10010001 6
b10010001 7
b1001100 5
1&
b10010000 %
b10010000 2
b10010111 (
b10010111 3
b10101110 )
b10101110 4
b100011010 0
#775
0&
#780
b10011011 !
b10011011 6
b10011011 7
b1001101 5
b11100100 9
1&
b10001111 %
b10001111 2
b10100011 (
b10100011 3
b10111100 )
b10111100 4
b100011101 0
#785
0&
#790
b11100111 9
b10010110 !
b10010110 6
b10010110 7
b1001110 5
1&
b1010101 %
b1010101 2
b10011101 (
b10011101 3
b11001001 )
b11001001 4
b100100000 0
#795
0&
#800
b10001010 !
b10001010 6
b10001010 7
b1001111 5
b11101010 9
1&
b110110 %
b110110 2
b10001111 (
b10001111 3
b11000110 )
b11000110 4
b100100011 0
#805
0&
#810
b11101101 9
b10001110 !
b10001110 6
b10001110 7
b1010000 5
1&
b111101 %
b111101 2
b10010100 (
b10010100 3
b11000101 )
b11000101 4
b100100110 0
#815
0&
#820
b10000010 !
b10000010 6
b10000010 7
b1010001 5
b11110000 9
1&
b111100 %
b111100 2
b10000101 (
b10000101 3
b10111100 )
b10111100 4
b100101001 0
#825
0&
#830
b11110011 9
b1111011 !
b1111011 6
b1111011 7
b1010010 5
1&
b1000110 %
b1000110 2
b1111001 (
b1111001 3
b10110110 )
b10110110 4
b100101100 0
#835
0&
#840
b10001001 !
b10001001 6
b10001001 7
b1010011 5
b11110110 9
1&
b10001011 %
b10001011 2
b10001010 (
b10001010 3
b10101100 )
b10101100 4
b100101111 0
#845
0&
#850
b11111001 9
b10001101 !
b10001101 6
b10001101 7
b1010100 5
1&
b10010111 %
b10010111 2
b10010011 (
b10010011 3
b10100111 )
b10100111 4
b100110010 0
#855
0&
#860
b10001011 !
b10001011 6
b10001011 7
b1010101 5
b11111100 9
1&
b10010110 %
b10010110 2
b10010001 (
b10010001 3
b10100011 )
b10100011 4
b100110101 0
#865
0&
#870
b11111111 9
b1010110 5
1&
b10011001 %
b10011001 2
b10010000 (
b10010000 3
b10100001 )
b10100001 4
b100111000 0
#875
0&
#880
b10001001 !
b10001001 6
b10001001 7
b1010111 5
b100000010 9
1&
b10011010 %
b10011010 2
b10010001 (
b10010001 3
b10011110 )
b10011110 4
b100111011 0
#885
0&
#890
b100000101 9
b10001110 !
b10001110 6
b10001110 7
b1011000 5
1&
b10011110 %
b10011110 2
b10010110 (
b10010110 3
b10100001 )
b10100001 4
b100111110 0
#895
0&
#900
b10001101 !
b10001101 6
b10001101 7
b1011001 5
b100001000 9
1&
b10011111 %
b10011111 2
b10010101 (
b10010101 3
b10100010 )
b10100010 4
b101000001 0
#905
0&
#910
b100001011 9
b10010010 !
b10010010 6
b10010010 7
b1011010 5
1&
b10100001 %
b10100001 2
b10010111 (
b10010111 3
b10101011 )
b10101011 4
b101000100 0
#915
0&
#920
b10011010 !
b10011010 6
b10011010 7
b1011011 5
b100001110 9
1&
b10101000 %
b10101000 2
b10011110 (
b10011110 3
b10111010 )
b10111010 4
b101000111 0
#925
0&
#930
b100010001 9
b10011000 !
b10011000 6
b10011000 7
b1011100 5
1&
b10100101 %
b10100101 2
b10011010 (
b10011010 3
b101001010 0
#935
0&
#940
b10010110 !
b10010110 6
b10010110 7
b1011101 5
b100010100 9
1&
b10100001 %
b10100001 2
b10011001 (
b10011001 3
b10110110 )
b10110110 4
b101001101 0
#945
0&
#950
b100010111 9
b1110110 !
b1110110 6
b1110110 7
b1011110 5
1&
b10001001 %
b10001001 2
b1111001 (
b1111001 3
b10001110 )
b10001110 4
b101010000 0
#955
0&
#960
b1100110 !
b1100110 6
b1100110 7
b1011111 5
b100011010 9
1&
b1111101 %
b1111101 2
b1101001 (
b1101001 3
b1111101 )
b1111101 4
b101010011 0
#965
0&
#970
b100011101 9
b1110011 !
b1110011 6
b1110011 7
b1100000 5
1&
b10000010 %
b10000010 2
b1110011 (
b1110011 3
b10001111 )
b10001111 4
b101010110 0
#975
0&
#980
b1111100 !
b1111100 6
b1111100 7
b1100001 5
b100100000 9
1&
b10001010 %
b10001010 2
b1111101 (
b1111101 3
b10011100 )
b10011100 4
b101011001 0
#985
0&
#990
b100100011 9
b10000011 !
b10000011 6
b10000011 7
b1100010 5
1&
b10010101 %
b10010101 2
b10000011 (
b10000011 3
b10100010 )
b10100010 4
b101011100 0
#995
0&
#1000
b10000000 !
b10000000 6
b10000000 7
b1100011 5
b100100110 9
1&
b10010111 %
b10010111 2
b10000000 (
b10000000 3
b10011111 )
b10011111 4
b101011111 0
#1005
0&
#1010
b100101001 9
b10000001 !
b10000001 6
b10000001 7
b1100100 5
1&
b10011010 %
b10011010 2
b10000010 (
b10000010 3
b10011110 )
b10011110 4
b101100010 0
#1015
0&
#1020
b10000011 !
b10000011 6
b10000011 7
b1100101 5
b100101100 9
1&
b10011100 %
b10011100 2
b10000110 (
b10000110 3
b10011111 )
b10011111 4
b101100101 0
#1025
0&
#1030
b100101111 9
b10000111 !
b10000111 6
b10000111 7
b1100110 5
1&
b10011101 %
b10011101 2
b10001010 (
b10001010 3
b10100010 )
b10100010 4
b101101000 0
#1035
0&
#1040
b10001100 !
b10001100 6
b10001100 7
b1100111 5
b100110010 9
1&
b10100000 %
b10100000 2
b10001110 (
b10001110 3
b10100110 )
b10100110 4
b101101011 0
#1045
0&
#1050
b100110101 9
b10010000 !
b10010000 6
b10010000 7
b1101000 5
1&
b10100011 %
b10100011 2
b10010010 (
b10010010 3
b10101010 )
b10101010 4
b101101110 0
#1055
0&
#1060
b10010100 !
b10010100 6
b10010100 7
b1101001 5
b100111000 9
1&
b10100110 %
b10100110 2
b10011001 (
b10011001 3
b10101110 )
b10101110 4
b101110001 0
#1065
0&
#1070
b100111011 9
b10010011 !
b10010011 6
b10010011 7
b1101010 5
1&
b10100100 %
b10100100 2
b10010111 (
b10010111 3
b10101101 )
b10101101 4
b101110100 0
#1075
0&
#1080
b10001110 !
b10001110 6
b10001110 7
b1101011 5
b100111110 9
1&
b10011110 %
b10011110 2
b10010010 (
b10010010 3
b10101000 )
b10101000 4
b101110111 0
#1085
0&
#1090
b101000001 9
b10001100 !
b10001100 6
b10001100 7
b1101100 5
1&
b10011100 %
b10011100 2
b10100011 )
b10100011 4
b101111010 0
#1095
0&
#1100
b10010101 !
b10010101 6
b10010101 7
b1101101 5
b101000100 9
1&
b10100000 %
b10100000 2
b10011100 (
b10011100 3
b10101000 )
b10101000 4
b101111101 0
#1105
0&
#1110
b101000111 9
b10011001 !
b10011001 6
b10011001 7
b1101110 5
1&
b10100010 %
b10100010 2
b10100000 (
b10100000 3
b10101100 )
b10101100 4
b110000000 0
#1115
0&
#1120
b10010101 !
b10010101 6
b10010101 7
b1101111 5
b101001010 9
1&
b10100001 %
b10100001 2
b10011100 (
b10011100 3
b10101001 )
b10101001 4
b110000011 0
#1125
0&
#1130
b101001101 9
b1110000 5
1&
b10100101 %
b10100101 2
b10011101 (
b10011101 3
b110000110 0
#1135
0&
#1140
b10000001 !
b10000001 6
b10000001 7
b1110001 5
b101010000 9
1&
b10001110 %
b10001110 2
b10001001 (
b10001001 3
b10010101 )
b10010101 4
b110001001 0
#1145
0&
#1150
b101010011 9
b110101 !
b110101 6
b110101 7
b1110010 5
1&
b111101 %
b111101 2
b111110 (
b111110 3
b111001 )
b111001 4
b110001100 0
#1155
0&
#1160
b110000 !
b110000 6
b110000 7
b1110011 5
b101010110 9
1&
b111011 %
b111011 2
b111011 (
b111011 3
b101111 )
b101111 4
b110001111 0
#1165
0&
#1170
b101011001 9
b101111 !
b101111 6
b101111 7
b1110100 5
1&
b111101 %
b111101 2
b111010 (
b111010 3
b101000 )
b101000 4
b110010010 0
#1175
0&
#1180
b101011 !
b101011 6
b101011 7
b1110101 5
b101011100 9
1&
b111110 %
b111110 2
b110111 (
b110111 3
b100010 )
b100010 4
b110010101 0
#1185
0&
